cyrillictolatin/__init__.py
cyrillictolatin/main.py
cyrillic_tolatin-0.0.2.dist-info/LICENSE.txt
cyrillic_tolatin-0.0.2.dist-info/METADATA
cyrillic_tolatin-0.0.2.dist-info/WHEEL
cyrillic_tolatin-0.0.2.dist-info/top_level.txt
cyrillic_tolatin-0.0.2.dist-info/RECORD
