Metadata-Version: 2.1
Name: cyrillic-tolatin
Version: 0.0.2
Summary: HI
Author: Ziyodulla Abdukarimov
Author-email: ZiyodullaDeveloper@gmail.com
Classifier: Programming Language :: Python :: 3
Classifier: License :: OSI Approved :: MIT License
Classifier: Operating System :: OS Independent
License-File: LICENSE.txt
